lofor/__init__.py
lofor/cli.py
lofor/manager/__init__.py
lofor/manager/config.py
lofor/server/__init__.py
lofor/server/http.py
lofor/server/serve.py
lofor-0.0.3.dist-info/METADATA
lofor-0.0.3.dist-info/WHEEL
lofor-0.0.3.dist-info/entry_points.txt
lofor-0.0.3.dist-info/top_level.txt
lofor-0.0.3.dist-info/RECORD
