Metadata-Version: 2.1
Name: lofor
Version: 0.0.3
Summary: Lofor is a lightweight development server which acts as a reverse proxy to solve your cors problems.
